IVOFilesConverter/__init__.py
IVOFilesConverter/main.py
IVOFilesConverter-1.0.6.dist-info/LICENSE
IVOFilesConverter-1.0.6.dist-info/METADATA
IVOFilesConverter-1.0.6.dist-info/WHEEL
IVOFilesConverter-1.0.6.dist-info/top_level.txt
IVOFilesConverter-1.0.6.dist-info/RECORD
