Metadata-Version: 2.1
Name: IVOFilesConverter
Version: 1.0.6
Summary: Конвертер файлов.
Home-page: https://github.com/Keynet123/IVOFilesConverter
Author: keynet
Author-email: viktorplay377@gmail.com
Project-URL: GitHub, https://github.com/Keynet123/IVOFilesConverter
Keywords: files ivofilesconverter
Classifier: Programming Language :: Python :: 3.11
Classifier: License :: OSI Approved :: MIT License
Classifier: Operating System :: OS Independent
Requires-Python: >=3.6
License-File: LICENSE
Requires-Dist: requests>=2.25.1
